Metadata-Version: 1.0
Name: roslaunch-api-wrapper
Version: 0.3
Summary: wrapper for rosalunch python api
Home-page: https://github.com/ACarfi/roslaunch-api-wrapper
Author: Alessandro Carfi
Author-email: carfi.alessandro@gmail.com
License: MIT
Platform: UNKNOWN
